src/__init__.py
src/main.py
src/style.py
src/res/style-codes.csv
terminal_styler-0.1.2.dist-info/METADATA
terminal_styler-0.1.2.dist-info/WHEEL
terminal_styler-0.1.2.dist-info/entry_points.txt
terminal_styler-0.1.2.dist-info/licenses/LICENSE
terminal_styler-0.1.2.dist-info/RECORD
