Metadata-Version: 2.1
Name: terminal-styler
Version: 0.1.2
Summary: CLI tool for adding foreground and background colours, as well as styles such as bold, underline, and more to your terminal output.
Project-URL: Homepage, https://github.com/SamJohn04/terminal-styler
Project-URL: Bug Tracker, https://github.com/SamJohn04/terminal-styler/issues
Author-email: Samuel John <samuel.john.codes@gmail.com>
License-File: LICENSE
Classifier: License :: OSI Approved :: MIT License
Classifier: Operating System :: OS Independent
Classifier: Programming Language :: Python :: 3
Requires-Python: >=3.7
